stream_benchmark/__init__.py
stream_benchmark/evals.py
stream_benchmark/tasks.py
stream_benchmark-0.1.4.dist-info/METADATA
stream_benchmark-0.1.4.dist-info/WHEEL
stream_benchmark-0.1.4.dist-info/licenses/LICENSE
stream_benchmark-0.1.4.dist-info/RECORD
