Metadata-Version: 2.4
Name: stream-benchmark
Version: 0.1.4
Summary: STREAM (Sequential Tasks Review to Evaluate Artificial Memory) is a benchmark of 12 diverse sequential tasks to assess neural networks’ memory. Scalable in complexity and sequence length, it covers pattern completion, copy tasks, forecasting, bracket matching, and sorting—ideal for comparing architectures on memory retention and sequential reasoning.
Author-email: Yannis Bendi-Ouis <yannis.bendiouis@gmail.com>
License: MIT License
License-File: LICENSE
Requires-Python: >=3.8
Requires-Dist: datasets
Requires-Dist: numpy
